{"Overtakes":{"63":[{"Timestamp":"2025-05-18T13:03:43.622Z","count":1},{"Timestamp":"2025-05-18T13:20:33.52Z","count":1},{"Timestamp":"2025-05-18T13:20:36.323Z","count":1},{"Timestamp":"2025-05-18T13:23:16.243Z","count":1},{"Timestamp":"2025-05-18T13:34:04.195Z","count":1},{"Timestamp":"2025-05-18T13:36:56.666Z","count":1},{"Timestamp":"2025-05-18T13:44:30.021Z","count":1},{"Timestamp":"2025-05-18T13:49:08.618Z","count":1},{"Timestamp":"2025-05-18T13:51:49.563Z","count":1},{"Timestamp":"2025-05-18T13:53:08.958Z","count":1},{"Timestamp":"2025-05-18T14:05:42.788Z","count":1},{"Timestamp":"2025-05-18T14:08:28.559Z","count":2}],"14":[{"Timestamp":"2025-05-18T13:03:43.747Z","count":1},{"Timestamp":"2025-05-18T13:18:40.616Z","count":1},{"Timestamp":"2025-05-18T13:23:19.571Z","count":1},{"Timestamp":"2025-05-18T13:34:15.101Z","count":1},{"Timestamp":"2025-05-18T13:44:20.036Z","count":6},{"Timestamp":"2025-05-18T14:05:59.585Z","count":1},{"Timestamp":"2025-05-18T14:24:10.528Z","count":1},{"Timestamp":"2025-05-18T14:26:51.204Z","count":1},{"Timestamp":"2025-05-18T14:29:27.971Z","count":1}],"10":[{"Timestamp":"2025-05-18T13:03:44.322Z","count":1},{"Timestamp":"2025-05-18T13:03:53.675Z","count":1},{"Timestamp":"2025-05-18T13:18:02.329Z","count":1},{"Timestamp":"2025-05-18T13:20:39.151Z","count":1},{"Timestamp":"2025-05-18T13:22:03.726Z","count":1},{"Timestamp":"2025-05-18T13:23:25.571Z","count":1},{"Timestamp":"2025-05-18T13:34:20.273Z","count":1},{"Timestamp":"2025-05-18T13:47:58.991Z","count":1},{"Timestamp":"2025-05-18T14:02:56.837Z","count":1},{"Timestamp":"2025-05-18T14:06:05.179Z","count":1},{"Timestamp":"2025-05-18T14:08:52.56Z","count":1},{"Timestamp":"2025-05-18T14:08:58.122Z","count":1}],"16":[{"Timestamp":"2025-05-18T13:03:44.423Z","count":1},{"Timestamp":"2025-05-18T13:03:48.378Z","count":1},{"Timestamp":"2025-05-18T13:04:04.43Z","count":1},{"Timestamp":"2025-05-18T13:07:08.376Z","count":1},{"Timestamp":"2025-05-18T13:19:14.207Z","count":2},{"Timestamp":"2025-05-18T13:20:31.873Z","count":2},{"Timestamp":"2025-05-18T13:23:14.024Z","count":1},{"Timestamp":"2025-05-18T13:31:25.164Z","count":1},{"Timestamp":"2025-05-18T13:34:02.054Z","count":1},{"Timestamp":"2025-05-18T13:34:12.492Z","count":1},{"Timestamp":"2025-05-18T13:39:35.721Z","count":1},{"Timestamp":"2025-05-18T13:47:39.862Z","count":1},{"Timestamp":"2025-05-18T13:49:05.55Z","count":1},{"Timestamp":"2025-05-18T13:55:43.583Z","count":1},{"Timestamp":"2025-05-18T13:59:47.128Z","count":1},{"Timestamp":"2025-05-18T14:08:04.516Z","count":1},{"Timestamp":"2025-05-18T14:10:03.385Z","count":1},{"Timestamp":"2025-05-18T14:30:19.421Z","count":1}],"44":[{"Timestamp":"2025-05-18T13:03:44.551Z","count":1},{"Timestamp":"2025-05-18T13:03:48.269Z","count":1},{"Timestamp":"2025-05-18T13:07:09.942Z","count":1},{"Timestamp":"2025-05-18T13:17:21.062Z","count":1},{"Timestamp":"2025-05-18T13:18:43.574Z","count":2},{"Timestamp":"2025-05-18T13:20:06.674Z","count":1},{"Timestamp":"2025-05-18T13:21:34.474Z","count":1},{"Timestamp":"2025-05-18T13:22:51.977Z","count":1},{"Timestamp":"2025-05-18T13:42:13.661Z","count":1},{"Timestamp":"2025-05-18T13:50:21.253Z","count":1},{"Timestamp":"2025-05-18T13:53:00.98Z","count":1},{"Timestamp":"2025-05-18T14:26:15.626Z","count":1},{"Timestamp":"2025-05-18T14:30:25.374Z","count":1},{"Timestamp":"2025-05-18T14:31:34.701Z","count":1}],"12":[{"Timestamp":"2025-05-18T13:03:44.742Z","count":1},{"Timestamp":"2025-05-18T13:03:48.566Z","count":2},{"Timestamp":"2025-05-18T13:07:09.32Z","count":1},{"Timestamp":"2025-05-18T13:17:20.312Z","count":1},{"Timestamp":"2025-05-18T13:18:43.126Z","count":2},{"Timestamp":"2025-05-18T13:20:06.198Z","count":1},{"Timestamp":"2025-05-18T13:21:34.018Z","count":1},{"Timestamp":"2025-05-18T13:22:51.352Z","count":1},{"Timestamp":"2025-05-18T13:42:13.06Z","count":1}],"6":[{"Timestamp":"2025-05-18T13:03:44.984Z","count":2},{"Timestamp":"2025-05-18T13:03:48.112Z","count":2},{"Timestamp":"2025-05-18T13:07:08.741Z","count":1},{"Timestamp":"2025-05-18T13:17:19.828Z","count":1},{"Timestamp":"2025-05-18T13:18:42.602Z","count":2},{"Timestamp":"2025-05-18T13:20:05.602Z","count":1},{"Timestamp":"2025-05-18T13:21:33.266Z","count":1},{"Timestamp":"2025-05-18T13:22:50.555Z","count":1},{"Timestamp":"2025-05-18T13:42:09.339Z","count":1}],"43":[{"Timestamp":"2025-05-18T13:03:45.032Z","count":2},{"Timestamp":"2025-05-18T13:03:49.222Z","count":2},{"Timestamp":"2025-05-18T13:05:05.586Z","count":1},{"Timestamp":"2025-05-18T13:16:04.908Z","count":1},{"Timestamp":"2025-05-18T13:17:27.406Z","count":1},{"Timestamp":"2025-05-18T13:17:32.572Z","count":1},{"Timestamp":"2025-05-18T13:18:54.649Z","count":2},{"Timestamp":"2025-05-18T13:20:12.454Z","count":1},{"Timestamp":"2025-05-18T13:20:17.595Z","count":1},{"Timestamp":"2025-05-18T13:21:40.03Z","count":1},{"Timestamp":"2025-05-18T13:23:03.055Z","count":1},{"Timestamp":"2025-05-18T13:41:26.742Z","count":1},{"Timestamp":"2025-05-18T13:44:39.442Z","count":3},{"Timestamp":"2025-05-18T13:47:44.737Z","count":1},{"Timestamp":"2025-05-18T14:06:07.76Z","count":1}],"27":[{"Timestamp":"2025-05-18T13:03:45.153Z","count":2},{"Timestamp":"2025-05-18T13:03:48.909Z","count":2},{"Timestamp":"2025-05-18T13:04:06.132Z","count":1},{"Timestamp":"2025-05-18T13:04:20.996Z","count":1},{"Timestamp":"2025-05-18T13:05:05.175Z","count":1},{"Timestamp":"2025-05-18T13:16:04.292Z","count":1},{"Timestamp":"2025-05-18T13:17:26.328Z","count":1},{"Timestamp":"2025-05-18T13:17:31.734Z","count":1},{"Timestamp":"2025-05-18T13:18:54.149Z","count":2},{"Timestamp":"2025-05-18T13:20:11.47Z","count":1},{"Timestamp":"2025-05-18T13:20:16.876Z","count":1},{"Timestamp":"2025-05-18T13:21:39.394Z","count":1},{"Timestamp":"2025-05-18T13:23:01.977Z","count":1},{"Timestamp":"2025-05-18T13:53:13.099Z","count":1},{"Timestamp":"2025-05-18T13:57:18.311Z","count":1},{"Timestamp":"2025-05-18T14:05:55.429Z","count":1}],"5":[{"Timestamp":"2025-05-18T13:03:45.296Z","count":2},{"Timestamp":"2025-05-18T13:03:48.503Z","count":1},{"Timestamp":"2025-05-18T13:04:11.94Z","count":1},{"Timestamp":"2025-05-18T13:07:13.395Z","count":1},{"Timestamp":"2025-05-18T13:17:23.312Z","count":1},{"Timestamp":"2025-05-18T13:18:51.587Z","count":2},{"Timestamp":"2025-05-18T13:24:54.567Z","count":1},{"Timestamp":"2025-05-18T13:34:24.545Z","count":1},{"Timestamp":"2025-05-18T13:48:02.851Z","count":1},{"Timestamp":"2025-05-18T14:06:10.791Z","count":1}],"30":[{"Timestamp":"2025-05-18T13:03:45.311Z","count":2},{"Timestamp":"2025-05-18T13:03:49.144Z","count":2},{"Timestamp":"2025-05-18T13:04:05.279Z","count":1},{"Timestamp":"2025-05-18T13:16:02.648Z","count":1},{"Timestamp":"2025-05-18T13:20:44.26Z","count":1},{"Timestamp":"2025-05-18T13:23:27.524Z","count":1},{"Timestamp":"2025-05-18T13:34:21.805Z","count":1},{"Timestamp":"2025-05-18T13:48:00.866Z","count":1},{"Timestamp":"2025-05-18T14:06:08.573Z","count":1},{"Timestamp":"2025-05-18T14:08:59.403Z","count":1},{"Timestamp":"2025-05-18T14:09:07.316Z","count":2}],"1":[{"Timestamp":"2025-05-18T13:03:46.298Z","count":1},{"Timestamp":"2025-05-18T13:03:51.831Z","count":1},{"Timestamp":"2025-05-18T13:03:53.066Z","count":19}],"4":[{"Timestamp":"2025-05-18T13:03:46.967Z","count":1},{"Timestamp":"2025-05-18T13:17:36.772Z","count":1},{"Timestamp":"2025-05-18T13:21:27.502Z","count":1},{"Timestamp":"2025-05-18T13:43:49.46Z","count":3},{"Timestamp":"2025-05-18T13:43:56.77Z","count":1},{"Timestamp":"2025-05-18T13:45:49.602Z","count":1},{"Timestamp":"2025-05-18T14:08:08.657Z","count":1},{"Timestamp":"2025-05-18T14:27:31.536Z","count":1}],"18":[{"Timestamp":"2025-05-18T13:03:47.566Z","count":1},{"Timestamp":"2025-05-18T13:18:42.038Z","count":2},{"Timestamp":"2025-05-18T13:20:04.837Z","count":1},{"Timestamp":"2025-05-18T13:21:32.53Z","count":1},{"Timestamp":"2025-05-18T13:24:49.877Z","count":1},{"Timestamp":"2025-05-18T13:34:18.695Z","count":1},{"Timestamp":"2025-05-18T13:44:24.536Z","count":5},{"Timestamp":"2025-05-18T13:44:28.411Z","count":1},{"Timestamp":"2025-05-18T14:06:02.752Z","count":1}],"31":[{"Timestamp":"2025-05-18T13:03:49.066Z","count":2},{"Timestamp":"2025-05-18T13:03:54.862Z","count":1},{"Timestamp":"2025-05-18T13:04:16.867Z","count":1},{"Timestamp":"2025-05-18T13:16:31.251Z","count":1},{"Timestamp":"2025-05-18T13:17:53.458Z","count":1},{"Timestamp":"2025-05-18T13:20:38.214Z","count":1},{"Timestamp":"2025-05-18T13:34:28.443Z","count":1}],"23":[{"Timestamp":"2025-05-18T13:03:53.05Z","count":1},{"Timestamp":"2025-05-18T13:18:41.588Z","count":2},{"Timestamp":"2025-05-18T13:20:03.895Z","count":1},{"Timestamp":"2025-05-18T13:21:31.084Z","count":1},{"Timestamp":"2025-05-18T13:42:00.881Z","count":1},{"Timestamp":"2025-05-18T13:45:58.742Z","count":1},{"Timestamp":"2025-05-18T14:08:04.781Z","count":1},{"Timestamp":"2025-05-18T14:30:14.155Z","count":1},{"Timestamp":"2025-05-18T14:34:13.809Z","count":1}],"87":[{"Timestamp":"2025-05-18T13:04:00.8Z","count":1},{"Timestamp":"2025-05-18T13:05:06.303Z","count":1},{"Timestamp":"2025-05-18T13:16:11.798Z","count":1},{"Timestamp":"2025-05-18T13:17:28.625Z","count":1},{"Timestamp":"2025-05-18T13:17:33.892Z","count":1},{"Timestamp":"2025-05-18T13:18:55.899Z","count":2},{"Timestamp":"2025-05-18T13:20:13.22Z","count":1},{"Timestamp":"2025-05-18T13:20:18.361Z","count":1},{"Timestamp":"2025-05-18T13:21:40.82Z","count":1},{"Timestamp":"2025-05-18T13:23:03.743Z","count":1},{"Timestamp":"2025-05-18T13:34:01.773Z","count":1},{"Timestamp":"2025-05-18T14:06:35.666Z","count":1},{"Timestamp":"2025-05-18T14:27:47.623Z","count":1}],"22":[{"Timestamp":"2025-05-18T13:05:08.286Z","count":1},{"Timestamp":"2025-05-18T13:16:12.266Z","count":1},{"Timestamp":"2025-05-18T13:17:34.771Z","count":2},{"Timestamp":"2025-05-18T13:18:56.712Z","count":2},{"Timestamp":"2025-05-18T13:20:19.142Z","count":2},{"Timestamp":"2025-05-18T13:21:41.739Z","count":1},{"Timestamp":"2025-05-18T13:23:04.649Z","count":1},{"Timestamp":"2025-05-18T13:34:03.523Z","count":1},{"Timestamp":"2025-05-18T13:47:42.171Z","count":1},{"Timestamp":"2025-05-18T13:55:59.615Z","count":1},{"Timestamp":"2025-05-18T14:01:26.045Z","count":1},{"Timestamp":"2025-05-18T14:05:57.523Z","count":1},{"Timestamp":"2025-05-18T14:22:51.002Z","count":1}],"55":[{"Timestamp":"2025-05-18T13:20:34.87Z","count":1},{"Timestamp":"2025-05-18T13:22:02.196Z","count":1},{"Timestamp":"2025-05-18T13:23:18.337Z","count":1},{"Timestamp":"2025-05-18T13:34:10.914Z","count":1},{"Timestamp":"2025-05-18T13:47:42.723Z","count":1},{"Timestamp":"2025-05-18T13:47:53.051Z","count":1},{"Timestamp":"2025-05-18T13:54:36.499Z","count":1},{"Timestamp":"2025-05-18T13:58:40.663Z","count":1},{"Timestamp":"2025-05-18T14:01:25.061Z","count":1},{"Timestamp":"2025-05-18T14:05:50.804Z","count":1},{"Timestamp":"2025-05-18T14:08:37.335Z","count":1}],"81":[{"Timestamp":"2025-05-18T13:23:09.555Z","count":1},{"Timestamp":"2025-05-18T13:27:18.199Z","count":1},{"Timestamp":"2025-05-18T13:28:37.68Z","count":1},{"Timestamp":"2025-05-18T13:29:56.756Z","count":1},{"Timestamp":"2025-05-18T13:32:45.207Z","count":1},{"Timestamp":"2025-05-18T13:38:06.031Z","count":1},{"Timestamp":"2025-05-18T13:39:27.781Z","count":1},{"Timestamp":"2025-05-18T13:40:48.824Z","count":1},{"Timestamp":"2025-05-18T13:42:07.63Z","count":1},{"Timestamp":"2025-05-18T13:43:53.076Z","count":1},{"Timestamp":"2025-05-18T13:58:12.067Z","count":1},{"Timestamp":"2025-05-18T14:07:54.752Z","count":1}]}}